pytest_git_diff/__init__.py
pytest_git_diff/_version.py
pytest_git_diff/affected_files.py
pytest_git_diff/changed_files.py
pytest_git_diff/dependencies.py
pytest_git_diff/plugin.py
pytest_git_diff/py.typed
pytest_git_diff-1.0.1.dist-info/LICENSE
pytest_git_diff-1.0.1.dist-info/METADATA
pytest_git_diff-1.0.1.dist-info/WHEEL
pytest_git_diff-1.0.1.dist-info/entry_points.txt
pytest_git_diff-1.0.1.dist-info/RECORD
