Metadata-Version: 2.1
Name: pytest-git-diff
Version: 1.0.1
Summary: Pytest plugin that allows the user to select the tests affected by a range of git commits
Home-page: https://github.com/sponja23/pytest-git-diff
License: MIT
Author: sponja23
Author-email: tomas.spognardi@gmail.com
Requires-Python: >=3.8,<4.0
Classifier: Framework :: Pytest
Classifier: Intended Audience :: Developers
Classifier: License :: OSI Approved :: MIT License
Classifier: Programming Language :: Python :: 3
Classifier: Programming Language :: Python :: 3.8
Classifier: Programming Language :: Python :: 3.9
Classifier: Programming Language :: Python :: 3.10
Classifier: Programming Language :: Python :: 3.11
Classifier: Programming Language :: Python :: 3.12
Classifier: Topic :: Software Development :: Testing
Requires-Dist: pydeps (>=1.12.20,<2.0.0)
Project-URL: Repository, https://github.com/sponja23/pytest-git-diff
